DEmap/TDE.py
DEmap/__init__.py
DEmap/config.py
DEmap/gp_utils.py
DEmap/kernels.py
DEmap/lmp_input_generator.py
DEmap/main.py
DEmap/plot_tools.py
DEmap/sphere_test.py
DEmap/sphere_utils.py
demap-0.15.0.dist-info/licenses/LICENSE.txt
demap-0.15.0.dist-info/METADATA
demap-0.15.0.dist-info/WHEEL
demap-0.15.0.dist-info/top_level.txt
demap-0.15.0.dist-info/RECORD
